dryco/__init__.py
dryco/decorators/__init__.py
dryco/decorators/main.py
dryco-0.0.1.dist-info/METADATA
dryco-0.0.1.dist-info/WHEEL
dryco-0.0.1.dist-info/licenses/LICENSE
dryco-0.0.1.dist-info/RECORD
